L09/mipsmem.v
//------------------------------------------------
// mipsmem.sv
// As proposed by Prof. Sarah Harris
// External unified memory used by MIPS multicycle
// processor.
//------------------------------------------------

module mem(input         clk, we,
           input  [31:0] a, wd,
           output [31:0] rd);

  reg  [31:0] RAM[63:0];

  // initialize memory with instructions
  initial
    begin
      $readmemh("memfile.dat",RAM,0,17);  // "memfile.dat" contains your 
                                          //    instructions in hex
                                          // you must create this file
    end

  assign rd = RAM[a[31:2]]; // word aligned

  always @(posedge clk)
    if (we)
      RAM[a[31:2]] <= wd;
endmodule

L09/mipsmulti_xx.v
module mips(input  clk, reset,
            output [31:0] adr, writedata,
            output memwrite,
            input [31:0] readdata);

  wire        zero, pcen, irwrite, regwrite,
               alusrca, iord, memtoreg, regdst;
  wire [1:0]  alusrcb, pcsrc;
  wire [2:0]  alucontrol;
  wire [5:0]  op, funct;

  controller c(clk, reset, op, funct, zero,
               pcen, memwrite, irwrite, regwrite,
               alusrca, iord, memtoreg, regdst, 
               alusrcb, pcsrc, alucontrol);
  datapath dp(clk, reset, 
              pcen, irwrite, regwrite,
              alusrca, iord, memtoreg, regdst,
              alusrcb, pcsrc, alucontrol,
              op, funct, zero,
              adr, writedata, readdata);
endmodule

module controller(input   clk, reset,
                  input [5:0] op, funct,
                  input  zero,
                  output pcen, memwrite, irwrite, regwrite,
                  output alusrca, iord, memtoreg, regdst,
                  output [1:0] alusrcb, pcsrc,
                  output [2:0] alucontrol);

  wire [1:0] aluop;
  wire branch, pcwrite, pcenprev;

  // Main Decoder and ALU Decoder subunits.
  maindec md(clk, reset, op,
             pcwrite, memwrite, irwrite, regwrite,
             alusrca, branch, iord, memtoreg, regdst,
             alusrcb, pcsrc, aluop);
  aludec  ad(funct, aluop, alucontrol);

  and and1 (pcenprev, zero, branch);
  or or1 (pcen, pcenprev, pcwrite);


endmodule

module aludec(input  [5:0] funct,
              input  [1:0] aluop,
              output reg [2:0] alucontrol);

always @(*)
	case(aluop)
		2'b00: alucontrol <= 3'b010;
		2'b01: alucontrol <= 3'b110;
		default: case (funct)
			6'b100000: alucontrol <= 3'b010;
			6'b100010: alucontrol <= 3'b110;
			6'b100100: alucontrol <= 3'b000;
			6'b100101: alucontrol <= 3'b001;
			6'b101010: alucontrol <= 3'b111;
			default: alucontrol <= 3'bxxx;
		endcase
	endcase
endmodule

module maindec(input  clk, reset, 
               input [5:0] op, 
               output pcwrite, memwrite, irwrite, regwrite,
               output alusrca, branch, iord, memtoreg, regdst,
               output [1:0] alusrcb, pcsrc,
               output [1:0] aluop);

  parameter   FETCH   = 4'b0000; // State 0
  parameter   DECODE  = 4'b0001; // State 1
  parameter   MEMADR  = 4'b0010;	// State 2
  parameter   MEMRD   = 4'b0011;	// State 3
  parameter   MEMWB   = 4'b0100;	// State 4
  parameter   MEMWR   = 4'b0101;	// State 5
  parameter   RTYPEEX = 4'b0110;	// State 6
  parameter   RTYPEWB = 4'b0111;	// State 7
  parameter   BEQEX   = 4'b1000;	// State 8
  parameter   ADDIEX  = 4'b1001;	// State 9
  parameter   ADDIWB  = 4'b1010;	// state 10
  parameter   JEX     = 4'b1011;	// State 11

  parameter   LW      = 6'b100011;	// Opcode for lw
  parameter   SW      = 6'b101011;	// Opcode for sw
  parameter   RTYPE   = 6'b000000;	// Opcode for R-type
  parameter   BEQ     = 6'b000100;	// Opcode for beq
  parameter   ADDI    = 6'b001000;	// Opcode for addi
  parameter   J       = 6'b000010;	// Opcode for j

  reg [3:0]  state, nextstate;
  reg [14:0] controls;

  // state register
  always @(posedge clk or posedge reset)			
    if(reset) state <= FETCH;
    else state <= nextstate;

  always @ (*)
    case(state)
      FETCH:   nextstate <= DECODE;
      DECODE:  case(op)
                 LW:      nextstate <= MEMADR;
                 SW:      nextstate <= MEMADR;
                 RTYPE:   nextstate <= RTYPEEX;
                 BEQ:     nextstate <= BEQEX;
                 ADDI:    nextstate <= ADDIEX;
                 J:       nextstate <= JEX;
                 default: nextstate <= 4'bx; // should never happen
               endcase
 		// Add code here
      MEMADR: case(op)
      		 LW:	  nextstate <= MEMRD;
		       SW:	  nextstate <= MEMWR;
	 endcase
      MEMRD:   nextstate <=  MEMWB;
      MEMWB:   nextstate <= FETCH;
      MEMWR:   nextstate <= FETCH;
      RTYPEEX: nextstate <= RTYPEWB;
      RTYPEWB: nextstate <= FETCH;
      BEQEX:   nextstate <= FETCH;
      ADDIEX:  nextstate <= ADDIWB;
      ADDIWB:  nextstate <= FETCH;
      JEX:     nextstate <= FETCH;
      default: nextstate <= 4'bx; // should never happen
    endcase

  // output logic
  assign {pcwrite, memwrite, irwrite, regwrite, alusrca, branch, iord, memtoreg, regdst,alusrcb, pcsrc, aluop} = controls;

  always @ (*)
    case(state)
      FETCH:   controls <= 15'h5010;
      DECODE:  controls <= 15'h0030;
      MEMADR: controls <= 15'h0420;
      MEMRD: controls <= 15'h0100;
      MEMWB: controls <= 15'h0880;
      MEMWR: controls <= 15'h2100;
      RTYPEEX: controls <= 15'h0402;
      RTYPEWB: controls <= 15'h0840;
      BEQEX: controls <= 15'h0605;
      ADDIEX: controls <= 15'h0420;
      ADDIWB: controls <= 15'h0800;
      JEX: controls <= 15'h4008; 
    
      default: controls <= 15'hxxxx; // should never happen
    endcase
endmodule


module datapath(input  clk, reset,
                input  pcen, irwrite, regwrite,
                input  alusrca, iord, memtoreg, regdst,
                input  [1:0]  alusrcb, pcsrc, 
                input  [2:0]  alucontrol,
                output [5:0]  op, funct,
                output zero,
                output [31:0] adr, writedata, 
                input  [31:0] readdata);

  // Below are the internal signals of the datapath module.

  wire [4:0]  writeregi;
  wire [4:0] a3;
  wire [31:0] pcnext, pc;
  wire [31:0] instr, data, srca, srcb;
  wire [31:0] a;
  wire [31:0] rd;
  wire [31:0] aluresult, aluout;
  wire [31:0] signimm;   // the sign-extended immediate
  wire [31:0] signimmsh;	// the sign-extended immediate shifted left by 2
  wire [31:0] wd3, rd1, rd2;
  wire [27:0] sl2temp;
  wire [31:0] pcjump;

  // op and funct fields to controller
  assign op = instr[31:26];
  assign funct = instr[5:0];

  mux2  #(5) muxA3 (instr[20:16],instr[15:11],regdst, a3);
  mux2  #(32) muxwd3 (aluout, data, memtoreg, wd3);
  regfile regfile_1 (clk, regwrite, instr[25:21], instr[20:16], a3, wd3, rd1, rd2);
  flopr  #(32) flop_a (clk, reset, rd1, a);
  flopr  #(32) flop_b (clk, reset, rd2, writedata);
  mux2  #(32) muxsrcA (pc, a, alusrca, srca );
  

  alu alumain (srca, srcb, alucontrol, aluresult, zero);
  flopr  #(32) flopaluout (clk, reset, aluresult, aluout);
  mux3  #(32) muxpcnext (aluresult, aluout, pcjump, pcsrc, pcnext);
  flopenr  #(32) floppc (clk, reset, pcen, pcnext, pc );
  mux2  #(32) muxadr (pc, aluout, iord, adr);
  mem mem1 (clk, memwrite, adr, writedata, rd);
  flopenr #(32) flopinstr (clk, reset, irwrite, rd, instr);
  flopr  #(32) flopdata (clk, reset, rd, data);
  signext signnextsignimm (instr[15:0], signimm);
  sl2 sl2signimmsh (signimm, signimmsh);
  mux4  #(32) muxsrcb (writedata, 32'b100, signimm, signimmsh,alusrcb, srcb);
  sl225 sl2pcjump (instr[25:0], sl2temp);
  assign pcjump = {pc[31:28] , sl2temp};
endmodule

module mux3 #(parameter WIDTH = 8)
		(input [WIDTH-1:0] d0, d1, d2,
		input [1:0] s,
		output [WIDTH-1:0] y);
	assign #1 y = s[1] ? d2 : (s[0] ? d1 : d0);
endmodule

module mux4 #(parameter WITDH = 8)
		(input [WITDH-1:0] d0,d1,d2,d3,
		input [1:0] s,
		output reg [WITDH-1:0] y);

	always @(*)
		case(s)
			2'b00: y <= d0;
			2'b01: y <= d1;
			2'b10: y <= d2;
			2'b11: y <= d3;
		endcase
endmodule

L09/alu.v
module alu( input [31:0] A, B, input [2:0] F,
            output reg [31:0] Y,
            output Zero);
 
    wire [31:0] S, Bout;
    
    assign Bout = F[2] ? ~B : B;
    assign S = A + Bout + F[2];

    always @ (*)
        case (F[1:0])
        2'b00: Y <= A & Bout;
        2'b01: Y <= A | Bout;
        2'b10: Y <= S;
        2'b11: Y <= S[31];
    endcase
    
    assign Zero = (Y == 32'b0);
endmodule

L09/topmulti.v
//------------------------------------------------
// topmulti.sv
// As proposed by Prof. David Harris
// and unified memory
//------------------------------------------------

module top(input         clk, reset, 
           output [31:0] writedata, adr, 
           output        memwrite);

  wire [31:0] readdata;
  
  // microprocessor (control & datapath)
  mips mips(clk, reset, adr, writedata, memwrite, readdata);

  // memory 
  mem mem(clk, memwrite, adr, writedata, readdata);

endmodule

L09/mipstest.v
//------------------------------------------------
// mipstest.sv
// Updated to SystemVerilog - Harris Harris version
// Testbench for MIPS processor
//------------------------------------------------

module testbench();

  reg        clk;
  reg        reset;

  wire [31:0] writedata, dataadr;
  wire        memwrite;

  // instantiate device to be tested
  top dut(clk, reset, writedata, dataadr, memwrite);
  
  // initialize test
  initial
    begin
      reset <= 1; # 22; reset <= 0;
    end

  // generate clock to sequence tests
  always
    begin
      clk <= 1; # 5; clk <= 0; # 5;
    end

  // check that 7 gets written to address 84
  always@(negedge clk)
    begin
      if(memwrite) begin
        if(dataadr === 84 & writedata === 7) begin
          $display("Simulation succeeded");
          $stop;
        end else if (dataadr !== 80) begin
          $display("Simulation failed");
          $stop;
        end
      end
    end
  initial begin
	  $dumpfile("mipstest.vcd");
	  $dumpvars;
  end
endmodule

L09/mipsparts.v
//------------------------------------------------
// mipsparts.sv
// Updated to SystemVerilog - Harris Harris version
// Components used in MIPS processor
//------------------------------------------------

module regfile(input         clk, 
               input         we3, 
               input  [4:0]  ra1, ra2, wa3, 
               input  [31:0] wd3, 
               output [31:0] rd1, rd2);

  reg [31:0] rf[31:0];

  // three ported register file
  // read two ports combinationally
  // write third port on riseing edge of clock
  // register 0 hardwired to 0

  always @(posedge clk)
    if (we3) rf[wa3] <= wd3;	

  assign rd1 = (ra1 != 0) ? rf[ra1] : 0;
  assign rd2 = (ra2 != 0) ? rf[ra2] : 0;
endmodule

module adder(input  [31:0] a, b,
             output [31:0] y);

  assign y = a + b;
endmodule

module sl2(input  [31:0] a,
           output [31:0] y);

  // shift left by 2
  assign y = {a[29:0], 2'b00};
endmodule

module sl225(input [25:0] a, output [27:0] y);
	assign y = {a, 2'b00};
endmodule

module signext(input  [15:0] a,
               output [31:0] y);
              
  assign y = {{16{a[15]}}, a};
endmodule

module flopr #(parameter WIDTH = 8)
              (input              clk, reset,
               input      [WIDTH-1:0] d, 
               output reg [WIDTH-1:0] q);

  always @(posedge clk, posedge reset)
    if (reset) q <= 0;
    else       q <= d;
endmodule

module flopenr #(parameter WIDTH = 8)
                (input              clk, reset,
                 input              en,
                 input      [WIDTH-1:0] d, 
                 output reg [WIDTH-1:0] q);
 
  always @(posedge clk, posedge reset)
    if      (reset) q <= 0;
    else if (en)    q <= d;
endmodule

module mux2 #(parameter WIDTH = 8)
             (input  [WIDTH-1:0] d0, d1, 
              input              s, 
              output [WIDTH-1:0] y);

  assign y = s ? d1 : d0; 
endmodule

L09/mipstest.vcd
$date
	Wed Jul 15 15:15:29 2020
$end
$version
	Icarus Verilog
$end
$timescale
	1s
$end
$scope module adder $end
$var wire 32 ! a [31:0] $end
$var wire 32 " b [31:0] $end
$var wire 32 # y [31:0] $end
$upscope $end
$scope module testbench $end
$var wire 32 $ writedata [31:0] $end
$var wire 1 % memwrite $end
$var wire 32 & dataadr [31:0] $end
$var reg 1 ' clk $end
$var reg 1 ( reset $end
$scope module dut $end
$var wire 1 ' clk $end
$var wire 1 ( reset $end
$var wire 32 ) writedata [31:0] $end
$var wire 32 * readdata [31:0] $end
$var wire 1 % memwrite $end
$var wire 32 + adr [31:0] $end
$scope module mem $end
$var wire 1 ' clk $end
$var wire 32 , rd [31:0] $end
$var wire 1 % we $end
$var wire 32 - wd [31:0] $end
$var wire 32 . a [31:0] $end
$upscope $end
$scope module mips $end
$var wire 1 ' clk $end
$var wire 32 / readdata [31:0] $end
$var wire 1 ( reset $end
$var wire 1 0 zero $end
$var wire 32 1 writedata [31:0] $end
$var wire 1 2 regwrite $end
$var wire 1 3 regdst $end
$var wire 2 4 pcsrc [1:0] $end
$var wire 1 5 pcen $end
$var wire 6 6 op [5:0] $end
$var wire 1 % memwrite $end
$var wire 1 7 memtoreg $end
$var wire 1 8 irwrite $end
$var wire 1 9 iord $end
$var wire 6 : funct [5:0] $end
$var wire 2 ; alusrcb [1:0] $end
$var wire 1 < alusrca $end
$var wire 3 = alucontrol [2:0] $end
$var wire 32 > adr [31:0] $end
$scope module c $end
$var wire 1 ' clk $end
$var wire 1 5 pcen $end
$var wire 1 ? pcenprev $end
$var wire 1 ( reset $end
$var wire 1 0 zero $end
$var wire 1 2 regwrite $end
$var wire 1 3 regdst $end
$var wire 1 @ pcwrite $end
$var wire 2 A pcsrc [1:0] $end
$var wire 6 B op [5:0] $end
$var wire 1 % memwrite $end
$var wire 1 7 memtoreg $end
$var wire 1 8 irwrite $end
$var wire 1 9 iord $end
$var wire 6 C funct [5:0] $end
$var wire 1 D branch $end
$var wire 2 E alusrcb [1:0] $end
$var wire 1 < alusrca $end
$var wire 2 F aluop [1:0] $end
$var wire 3 G alucontrol [2:0] $end
$scope module ad $end
$var wire 6 H funct [5:0] $end
$var wire 2 I aluop [1:0] $end
$var reg 3 J alucontrol [2:0] $end
$upscope $end
$scope module md $end
$var wire 1 ' clk $end
$var wire 1 ( reset $end
$var wire 1 2 regwrite $end
$var wire 1 3 regdst $end
$var wire 1 @ pcwrite $end
$var wire 2 K pcsrc [1:0] $end
$var wire 6 L op [5:0] $end
$var wire 1 % memwrite $end
$var wire 1 7 memtoreg $end
$var wire 1 8 irwrite $end
$var wire 1 9 iord $end
$var wire 1 D branch $end
$var wire 2 M alusrcb [1:0] $end
$var wire 1 < alusrca $end
$var wire 2 N aluop [1:0] $end
$var reg 15 O controls [14:0] $end
$var reg 4 P nextstate [3:0] $end
$var reg 4 Q state [3:0] $end
$upscope $end
$upscope $end
$scope module dp $end
$var wire 3 R alucontrol [2:0] $end
$var wire 1 < alusrca $end
$var wire 2 S alusrcb [1:0] $end
$var wire 1 ' clk $end
$var wire 1 9 iord $end
$var wire 1 8 irwrite $end
$var wire 1 7 memtoreg $end
$var wire 1 T memwrite $end
$var wire 1 5 pcen $end
$var wire 2 U pcsrc [1:0] $end
$var wire 32 V readdata [31:0] $end
$var wire 1 3 regdst $end
$var wire 1 2 regwrite $end
$var wire 1 ( reset $end
$var wire 1 0 zero $end
$var wire 32 W writedata [31:0] $end
$var wire 32 X wd3 [31:0] $end
$var wire 32 Y srcb [31:0] $end
$var wire 32 Z srca [31:0] $end
$var wire 28 [ sl2temp [27:0] $end
$var wire 32 \ signimmsh [31:0] $end
$var wire 32 ] signimm [31:0] $end
$var wire 32 ^ rd2 [31:0] $end
$var wire 32 _ rd1 [31:0] $end
$var wire 32 ` rd [31:0] $end
$var wire 32 a pcnext [31:0] $end
$var wire 32 b pcjump [31:0] $end
$var wire 32 c pc [31:0] $end
$var wire 6 d op [5:0] $end
$var wire 32 e instr [31:0] $end
$var wire 6 f funct [5:0] $end
$var wire 32 g data [31:0] $end
$var wire 32 h aluresult [31:0] $end
$var wire 32 i aluout [31:0] $end
$var wire 32 j adr [31:0] $end
$var wire 5 k a3 [4:0] $end
$var wire 32 l a [31:0] $end
$scope module alumain $end
$var wire 3 m F [2:0] $end
$var wire 1 0 Zero $end
$var wire 32 n S [31:0] $end
$var wire 32 o Bout [31:0] $end
$var wire 32 p B [31:0] $end
$var wire 32 q A [31:0] $end
$var reg 32 r Y [31:0] $end
$upscope $end
$scope module flop_a $end
$var wire 1 ' clk $end
$var wire 1 ( reset $end
$var wire 32 s d [31:0] $end
$var reg 32 t q [31:0] $end
$upscope $end
$scope module flop_b $end
$var wire 1 ' clk $end
$var wire 1 ( reset $end
$var wire 32 u d [31:0] $end
$var reg 32 v q [31:0] $end
$upscope $end
$scope module flopaluout $end
$var wire 1 ' clk $end
$var wire 32 w d [31:0] $end
$var wire 1 ( reset $end
$var reg 32 x q [31:0] $end
$upscope $end
$scope module flopdata $end
$var wire 1 ' clk $end
$var wire 1 ( reset $end
$var wire 32 y d [31:0] $end
$var reg 32 z q [31:0] $end
$upscope $end
$scope module flopinstr $end
$var wire 1 ' clk $end
$var wire 1 8 en $end
$var wire 1 ( reset $end
$var wire 32 { d [31:0] $end
$var reg 32 | q [31:0] $end
$upscope $end
$scope module floppc $end
$var wire 1 ' clk $end
$var wire 1 5 en $end
$var wire 1 ( reset $end
$var wire 32 } d [31:0] $end
$var reg 32 ~ q [31:0] $end
$upscope $end
$scope module mem1 $end
$var wire 1 ' clk $end
$var wire 32 !" rd [31:0] $end
$var wire 32 "" wd [31:0] $end
$var wire 1 T we $end
$var wire 32 #" a [31:0] $end
$upscope $end
$scope module muxA3 $end
$var wire 5 $" d0 [4:0] $end
$var wire 5 %" d1 [4:0] $end
$var wire 1 3 s $end
$var wire 5 &" y [4:0] $end
$upscope $end
$scope module muxadr $end
$var wire 32 '" d0 [31:0] $end
$var wire 32 (" d1 [31:0] $end
$var wire 1 9 s $end
$var wire 32 )" y [31:0] $end
$upscope $end
$scope module muxpcnext $end
$var wire 32 *" d0 [31:0] $end
$var wire 32 +" d1 [31:0] $end
$var wire 32 ," d2 [31:0] $end
$var wire 2 -" s [1:0] $end
$var wire 32 ." y [31:0] $end
$upscope $end
$scope module muxsrcA $end
$var wire 32 /" d0 [31:0] $end
$var wire 32 0" d1 [31:0] $end
$var wire 1 < s $end
$var wire 32 1" y [31:0] $end
$upscope $end
$scope module muxsrcb $end
$var wire 32 2" d0 [31:0] $end
$var wire 32 3" d1 [31:0] $end
$var wire 2 4" s [1:0] $end
$var wire 32 5" d3 [31:0] $end
$var wire 32 6" d2 [31:0] $end
$var reg 32 7" y [31:0] $end
$upscope $end
$scope module muxwd3 $end
$var wire 32 8" d0 [31:0] $end
$var wire 32 9" d1 [31:0] $end
$var wire 1 7 s $end
$var wire 32 :" y [31:0] $end
$upscope $end
$scope module regfile_1 $end
$var wire 1 ' clk $end
$var wire 5 ;" ra1 [4:0] $end
$var wire 5 <" ra2 [4:0] $end
$var wire 5 =" wa3 [4:0] $end
$var wire 32 >" wd3 [31:0] $end
$var wire 1 2 we3 $end
$var wire 32 ?" rd2 [31:0] $end
$var wire 32 @" rd1 [31:0] $end
$upscope $end
$scope module signnextsignimm $end
$var wire 16 A" a [15:0] $end
$var wire 32 B" y [31:0] $end
$upscope $end
$scope module sl2pcjump $end
$var wire 26 C" a [25:0] $end
$var wire 28 D" y [27:0] $end
$upscope $end
$scope module sl2signimmsh $end
$var wire 32 E" a [31:0] $end
$var wire 32 F" y [31:0] $end
$upscope $end
$upscope $end
$upscope $end
$upscope $end
$upscope $end
$enddefinitions $end
#0
$dumpvars
b0 F"
b0 E"
b0 D"
b0 C"
b0 B"
b0 A"
b0 @"
b0 ?"
b0 >"
b0 ="
b0 <"
b0 ;"
b0 :"
b0 9"
b0 8"
b100 7"
b0 6"
b0 5"
b1 4"
b100 3"
b0 2"
b0 1"
b0 0"
b0 /"
bx ."
b0 -"
b0 ,"
b0 +"
b100 *"
b0 )"
b0 ("
b0 '"
b0 &"
b0 %"
b0 $"
b0 #"
b0 ""
b100000000000100000000000000101 !"
b0 ~
bx }
b0 |
b100000000000100000000000000101 {
b0 z
b100000000000100000000000000101 y
b0 x
b100 w
b0 v
b0 u
b0 t
b0 s
b100 r
b0 q
b100 p
b100 o
b100 n
b10 m
b0 l
b0 k
b0 j
b0 i
b100 h
b0 g
b0 f
b0 e
b0 d
b0 c
b0 b
bx a
b100000000000100000000000000101 `
b0 _
b0 ^
b0 ]
b0 \
b0 [
b0 Z
b100 Y
b0 X
b0 W
b100000000000100000000000000101 V
b0 U
zT
b1 S
b10 R
b0 Q
b1 P
b101000000010000 O
b0 N
b1 M
b0 L
b0 K
b10 J
b0 I
b0 H
b10 G
b0 F
b1 E
0D
b0 C
b0 B
b0 A
1@
0?
b0 >
b10 =
0<
b1 ;
b0 :
09
18
07
b0 6
15
b0 4
03
02
b0 1
00
b100000000000100000000000000101 /
b0 .
b0 -
b100000000000100000000000000101 ,
b0 +
b100000000000100000000000000101 *
b0 )
1(
1'
b0 &
0%
b0 $
bx #
bz "
bz !
$end
#1
b100 a
b100 }
b100 ."
#5
0'
#10
1'
#15
0'
#20
1'
#22
0(
#25
0'
#30
b10100 o
b10100 Y
b10100 p
b10100 7"
05
0@
08
b11 ;
b11 E
b11 M
b11 S
b11 4"
b11000 h
b11000 r
b11000 w
b11000 *"
b110000 O
b1001 P
b10100 \
b10100 5"
b10100 F"
bx ^
bx u
bx ?"
b10 k
b10 &"
b10 ="
b100000000000110000000000001100 `
b100000000000110000000000001100 y
b100000000000110000000000001100 {
b100000000000110000000000001100 !"
b100000000000110000000000001100 *
b100000000000110000000000001100 ,
b100000000000110000000000001100 /
b100000000000110000000000001100 V
b10000000000000010100 b
b10000000000000010100 ,"
b10000000000000010100 [
b10000000000000010100 D"
b100000000000000101 C"
b101 ]
b101 6"
b101 B"
b101 E"
b101 A"
b10 <"
b10 $"
b101 :
b101 C
b101 H
b101 f
b1000 6
b1000 B
b1000 L
b1000 d
b100 &
b100 +
b100 .
b100 >
b100 j
b100 #"
b100 )"
b11000 n
b100 Z
b100 q
b100 1"
b100 X
b100 :"
b100 >"
b100000000000100000000000000101 g
b100000000000100000000000000101 z
b100000000000100000000000000101 9"
b100000000000100000000000000101 e
b100000000000100000000000000101 |
b100 c
b100 ~
b100 '"
b100 /"
b100 i
b100 x
b100 ("
b100 +"
b100 8"
b1 Q
1'
#31
b11000 a
b11000 }
b11000 ."
#35
0'
#40
b101 o
b101 h
b101 r
b101 w
b101 *"
b101 Y
b101 p
b101 7"
b101 n
b0 Z
b0 q
b0 1"
1<
b10 ;
b10 E
b10 M
b10 S
b10 4"
b10000100000 O
b1010 P
b11000 X
b11000 :"
b11000 >"
b1001 Q
bx $
bx )
bx -
bx 1
bx W
bx v
bx ""
bx 2"
b11000 i
b11000 x
b11000 ("
b11000 +"
b11000 8"
b100000000000110000000000001100 g
b100000000000110000000000001100 z
b100000000000110000000000001100 9"
1'
#41
b101 a
b101 }
b101 ."
#45
0'
#50
x0
bx o
bx h
bx r
bx w
bx *"
bx Y
bx p
bx 7"
bx n
b100 Z
b100 q
b100 1"
12
0<
b0 ;
b0 E
b0 M
b0 S
b0 4"
b100000000000 O
b0 P
b101 X
b101 :"
b101 >"
b101 i
b101 x
b101 ("
b101 +"
b101 8"
b1010 Q
1'
#51
bx a
bx }
bx ."
#55
0'
#60
00
b1000 h
b1000 r
b1000 w
b1000 *"
b1000 n
b100 o
b100 Y
b100 p
b100 7"
15
1@
18
02
b1 ;
b1 E
b1 M
b1 S
b1 4"
b101000000010000 O
b1 P
b101 ^
b101 u
b101 ?"
bx X
bx :"
bx >"
b0 Q
bx i
bx x
bx ("
bx +"
bx 8"
1'
#61
b1000 a
b1000 }
b1000 ."
#65
0'
#70
b110000 o
b110000 Y
b110000 p
b110000 7"
05
0@
08
b11 ;
b11 E
b11 M
b11 S
b11 4"
b111000 h
b111000 r
b111000 w
b111000 *"
b110000 O
b1001 P
b110000 \
b110000 5"
b110000 F"
bx ^
bx u
bx ?"
b11 k
b11 &"
b11 ="
b100000011001111111111111110111 `
b100000011001111111111111110111 y
b100000011001111111111111110111 {
b100000011001111111111111110111 !"
b100000011001111111111111110111 *
b100000011001111111111111110111 ,
b100000011001111111111111110111 /
b100000011001111111111111110111 V
b11000000000000110000 b
b11000000000000110000 ,"
b11000000000000110000 [
b11000000000000110000 D"
b110000000000001100 C"
b1100 ]
b1100 6"
b1100 B"
b1100 E"
b1100 A"
b11 <"
b11 $"
b1100 :
b1100 C
b1100 H
b1100 f
b1000 &
b1000 +
b1000 .
b1000 >
b1000 j
b1000 #"
b1000 )"
b111000 n
b1000 Z
b1000 q
b1000 1"
b1000 X
b1000 :"
b1000 >"
b100000000000110000000000001100 e
b100000000000110000000000001100 |
b1000 c
b1000 ~
b1000 '"
b1000 /"
b1000 i
b1000 x
b1000 ("
b1000 +"
b1000 8"
b101 $
b101 )
b101 -
b101 1
b101 W
b101 v
b101 ""
b101 2"
b1 Q
1'
#71
b111000 a
b111000 }
b111000 ."
#75
0'
#80
b1100 o
b1100 h
b1100 r
b1100 w
b1100 *"
b1100 Y
b1100 p
b1100 7"
b1100 n
b0 Z
b0 q
b0 1"
1<
b10 ;
b10 E
b10 M
b10 S
b10 4"
b10000100000 O
b1010 P
b111000 X
b111000 :"
b111000 >"
b1001 Q
bx $
bx )
bx -
bx 1
bx W
bx v
bx ""
bx 2"
b111000 i
b111000 x
b111000 ("
b111000 +"
b111000 8"
b100000011001111111111111110111 g
b100000011001111111111111110111 z
b100000011001111111111111110111 9"
1'
#81
b1100 a
b1100 }
b1100 ."
#85
0'
#90
x0
bx o
bx h
bx r
bx w
bx *"
bx Y
bx p
bx 7"
bx n
b1000 Z
b1000 q
b1000 1"
12
0<
b0 ;
b0 E
b0 M
b0 S
b0 4"
b100000000000 O
b0 P
b1100 X
b1100 :"
b1100 >"
b1100 i
b1100 x
b1100 ("
b1100 +"
b1100 8"
b1010 Q
1'
#91
bx a
bx }
bx ."
#95
0'
#100
00
b1100 h
b1100 r
b1100 w
b1100 *"
b1100 n
b100 o
b100 Y
b100 p
b100 7"
15
1@
18
02
b1 ;
b1 E
b1 M
b1 S
b1 4"
b101000000010000 O
b1 P
b1100 ^
b1100 u
b1100 ?"
bx X
bx :"
bx >"
b0 Q
bx i
bx x
bx ("
bx +"
bx 8"
1'
#101
b1100 a
b1100 }
b1100 ."
#105
0'
#110
b11111111111111111111111111011100 o
b11111111111111111111111111011100 Y
b11111111111111111111111111011100 p
b11111111111111111111111111011100 7"
05
0@
08
b11 ;
b11 E
b11 M
b11 S
b11 4"
b11111111111111111111111111101000 h
b11111111111111111111111111101000 r
b11111111111111111111111111101000 w
b11111111111111111111111111101000 *"
b110000 O
b1001 P
b11111111111111111111111111011100 \
b11111111111111111111111111011100 5"
b11111111111111111111111111011100 F"
bx ^
bx u
bx ?"
b1100 _
b1100 s
b1100 @"
b111 k
b111 &"
b111 ="
b111000100010000000100101 `
b111000100010000000100101 y
b111000100010000000100101 {
b111000100010000000100101 !"
b111000100010000000100101 *
b111000100010000000100101 ,
b111000100010000000100101 /
b111000100010000000100101 V
b1100111111111111111011100 b
b1100111111111111111011100 ,"
b1100111111111111111011100 [
b1100111111111111111011100 D"
b11001111111111111110111 C"
b11111111111111111111111111110111 ]
b11111111111111111111111111110111 6"
b11111111111111111111111111110111 B"
b11111111111111111111111111110111 E"
b1111111111110111 A"
b111 <"
b11 ;"
b11111 %"
b111 $"
b110111 :
b110111 C
b110111 H
b110111 f
b1100 &
b1100 +
b1100 .
b1100 >
b1100 j
b1100 #"
b1100 )"
b11111111111111111111111111101000 n
b1100 Z
b1100 q
b1100 1"
b1100 X
b1100 :"
b1100 >"
b100000011001111111111111110111 e
b100000011001111111111111110111 |
b1100 c
b1100 ~
b1100 '"
b1100 /"
b1100 i
b1100 x
b1100 ("
b1100 +"
b1100 8"
b1100 $
b1100 )
b1100 -
b1100 1
b1100 W
b1100 v
b1100 ""
b1100 2"
b1 Q
1'
#111
b11111111111111111111111111101000 a
b11111111111111111111111111101000 }
b11111111111111111111111111101000 ."
#115
0'
#120
b11 h
b11 r
b11 w
b11 *"
b11 n
b11111111111111111111111111110111 o
b11111111111111111111111111110111 Y
b11111111111111111111111111110111 p
b11111111111111111111111111110111 7"
1<
b10 ;
b10 E
b10 M
b10 S
b10 4"
b10000100000 O
b1010 P
b11111111111111111111111111101000 X
b11111111111111111111111111101000 :"
b11111111111111111111111111101000 >"
b1001 Q
b1100 l
b1100 t
b1100 0"
bx $
bx )
bx -
bx 1
bx W
bx v
bx ""
bx 2"
b11111111111111111111111111101000 i
b11111111111111111111111111101000 x
b11111111111111111111111111101000 ("
b11111111111111111111111111101000 +"
b11111111111111111111111111101000 8"
b111000100010000000100101 g
b111000100010000000100101 z
b111000100010000000100101 9"
1'
#121
b11 a
b11 }
b11 ."
#125
0'
#130
x0
bx h
bx r
bx w
bx *"
bx n
bx o
bx Y
bx p
bx 7"
12
0<
b0 ;
b0 E
b0 M
b0 S
b0 4"
b100000000000 O
b0 P
b11 X
b11 :"
b11 >"
b11 i
b11 x
b11 ("
b11 +"
b11 8"
b1010 Q
1'
#131
bx a
bx }
bx ."
#135
0'
#140
00
b10000 h
b10000 r
b10000 w
b10000 *"
b10000 n
b100 o
b100 Y
b100 p
b100 7"
15
1@
18
02
b1 ;
b1 E
b1 M
b1 S
b1 4"
b101000000010000 O
b1 P
b11 ^
b11 u
b11 ?"
bx X
bx :"
bx >"
b0 Q
bx i
bx x
bx ("
bx +"
bx 8"
1'
#141
b10000 a
b10000 }
b10000 ."
#145
0'
